pydecisions/__init__.py
pydecisions/pydecisions.py
pydecisions-0.2.4.dist-info/METADATA
pydecisions-0.2.4.dist-info/RECORD
pydecisions-0.2.4.dist-info/WHEEL
pydecisions-0.2.4.dist-info/top_level.txt
